batspy/__init__.py
batspy/batspy.py
batspy-0.1.3.dist-info/METADATA
batspy-0.1.3.dist-info/WHEEL
batspy-0.1.3.dist-info/top_level.txt
batspy-0.1.3.dist-info/RECORD
